pmpg-1.0.data/scripts/pmpg
src/__init__.py
src/projectdir.py
src/projrunner.py
src/util/__init__.py
src/util/projconfig.py
src/util/repository.py
pmpg-1.0.dist-info/METADATA
pmpg-1.0.dist-info/WHEEL
pmpg-1.0.dist-info/top_level.txt
pmpg-1.0.dist-info/RECORD
